neze_webcli-0.6.post4.dist-info/METADATA
neze_webcli-0.6.post4.dist-info/RECORD
neze_webcli-0.6.post4.dist-info/WHEEL
neze_webcli-0.6.post4.dist-info/entry_points.txt
neze_webcli-0.6.post4.dist-info/top_level.txt
webcli/__init__.py
webcli/__main__.py
webcli/__version__.py
webcli/_error.py
webcli/api/__init__.py
webcli/api/__main__.py
webcli/api/gitlab.py
webcli/api/transmission/__init__.py
webcli/api/transmission/_api.py
webcli/api/transmission/_functions.py
webcli/api/transmission/spec.py
webcli/cli/__init__.py
webcli/cli/__main__.py
webcli/cli/wcc.py
webcli/cli/git_piptag/__init__.py
webcli/cli/git_piptag/__main__.py
webcli/cli/gitlab/__init__.py
webcli/cli/gitlab/__main__.py
webcli/cli/patches/__init__.py
webcli/cli/patches/config.py
webcli/cli/patches/display.py
webcli/cli/transmission/__init__.py
webcli/cli/transmission/__main__.py
webcli/data/__init__.py
webcli/data/_error.py
webcli/data/config/__init__.py
webcli/data/config/_config.py
webcli/data/config/_error.py
webcli/data/config/_names.py
webcli/data/config/_spec.py
webcli/data/cookie/__init__.py
webcli/data/cookie/__main__.py
webcli/data/cookie/_cookie.py
webcli/data/cookie/_error.py
webcli/data/cookie/_names.py
webcli/data/files/__init__.py
webcli/data/files/_error.py
webcli/data/files/_file.py
webcli/data/secrets/__init__.py
webcli/data/secrets/_error.py
webcli/data/secrets/_pass.py
webcli/data/secrets/_secrets.py
webcli/utils/__init__.py
webcli/utils/choices.py
webcli/utils/dataparsers.py
webcli/utils/docker.py
webcli/utils/iter.py
webcli/utils/rodict.py
