Metadata-Version: 2.1
Name: neze-webcli
Version: 0.6.post4
Summary: Utility suite
Home-page: UNKNOWN
Author: ('Clement Durand',)
Author-email: durand.clement.13@gmail.com
License: UNKNOWN
Platform: UNKNOWN
Classifier: License :: OSI Approved :: GNU General Public License v3 or later (GPLv3+)
Classifier: Programming Language :: Python :: 3 :: Only
Classifier: Topic :: Utilities
Requires-Dist: requests
Requires-Dist: PyYAML
Requires-Dist: python-dateutil
Requires-Dist: pep440nz
